[{"website": "http://gulflabor.org/", "photo": "20140407144649.png", "content": "https://wayback.archive-it.org/1068/20140407144649/http://gulflabor.org/", "start": "2014-04-07", "time": "14:46:49", "id": "1"}, 
{"website": "http://gulflabor.org/", "photo": "20140623185352.png", "content": "https://wayback.archive-it.org/1068/20140623185352/http://gulflabor.org/", "start": "2014-06-23", "time": "18:53:52", "id": "2"}, 
{"website": "http://gulflabor.org/", "photo": "20141001174322.png", "content": "https://wayback.archive-it.org/1068/20141001174322/http://gulflabor.org/", "start": "2014-10-01", "time": "17:43:22", "id": "3"},
 {"website": "http://gulflabor.org/", "photo": "20150101193325.png", "content": "https://wayback.archive-it.org/1068/20150101193325/http://gulflabor.org/", "start": "2015-01-01", "time": "19:33:25", "id": "4"}, 
 {"website": "http://gulflabor.org/", "photo": "20150402220157.png", "content": "https://wayback.archive-it.org/1068/20150402220157/http://gulflabor.org/", "start": "2015-04-02", "time": "22:01:57", "id": "5"}, 
 {"website": "http://gulflabor.org/", "photo": "20150701214624.png", "content": "https://wayback.archive-it.org/1068/20150701214624/http://gulflabor.org/", "start": "2015-07-01", "time": "21:46:24", "id": "6"}, 
 {"website": "http://gulflabor.org/", "photo": "20151001211715.png", "content": "https://wayback.archive-it.org/1068/20151001211715/http://gulflabor.org/", "start": "2015-10-01", "time": "21:17:15", "id": "7"},
 {"website": "http://gulflabor.org/", "photo": "20160104194953.png", "content": "https://wayback.archive-it.org/1068/20160104194953/http://gulflabor.org/", "start": "2016-01-04", "time": "19:49:53", "id": "8"},
 {"website": "http://gulflabor.org/", "photo": "20160704195152.png", "content": "https://wayback.archive-it.org/1068/20160704195152/http://gulflabor.org/", "start": "2016-07-04", "time": "19:51:52", "id": "9"},  
  
 {"website": "http://gulflabor.org/", "photo": "20161014205246.png", "content": "https://wayback.archive-it.org/1068/20161014205246/http://gulflabor.org/", "start": "2016-10-14", "time": "20:52:46", "id": "10"}, 
 {"website": "http://gulflabor.org/", "photo": "20170114205222.png", "content": "https://wayback.archive-it.org/1068/20170114205222/http://gulflabor.org/", "start": "2017-01-14", "time": "20:52:22", "id": "11"}]